qualibrate/__init__.py
qualibrate/__main__.py
qualibrate/config/__init__.py
qualibrate/config/resolvers.py
qualibrate/models/__init__.py
qualibrate/models/execution_history.py
qualibrate/models/node_status.py
qualibrate/models/operational_condition.py
qualibrate/models/outcome.py
qualibrate/models/run_mode.py
qualibrate/models/run_summary/__init__.py
qualibrate/models/run_summary/base.py
qualibrate/models/run_summary/graph.py
qualibrate/models/run_summary/node.py
qualibrate/models/run_summary/run_error.py
qualibrate/orchestration/__init__.py
qualibrate/orchestration/basic_orchestrator.py
qualibrate/orchestration/qualibration_orchestrator.py
qualibrate/parameters.py
qualibrate/py.typed
qualibrate/q_runnnable.py
qualibrate/qualibration_graph.py
qualibrate/qualibration_library.py
qualibrate/qualibration_node.py
qualibrate/runnables/__init__.py
qualibrate/runnables/node_context.py
qualibrate/runnables/run_action/__init__.py
qualibrate/runnables/run_action/action.py
qualibrate/runnables/run_action/action_manager.py
qualibrate/runnables/run_action/utils.py
qualibrate/runnables/runnable_collection.py
qualibrate/storage/__init__.py
qualibrate/storage/local_storage_manager.py
qualibrate/storage/storage_manager.py
qualibrate/utils/__init__.py
qualibrate/utils/exceptions.py
qualibrate/utils/graph_building.py
qualibrate/utils/logger_m.py
qualibrate/utils/logger_utils/__init__.py
qualibrate/utils/logger_utils/filters.py
qualibrate/utils/logger_utils/fotmatters.py
qualibrate/utils/logger_utils/handlers.py
qualibrate/utils/naming.py
qualibrate/utils/node/__init__.py
qualibrate/utils/node/comined_method.py
qualibrate/utils/node/content.py
qualibrate/utils/node/loaders/__init__.py
qualibrate/utils/node/loaders/base_loader.py
qualibrate/utils/node/loaders/image_loader.py
qualibrate/utils/node/loaders/json_loader.py
qualibrate/utils/node/loaders/numpy_array_loader.py
qualibrate/utils/node/loaders/quam_loader.py
qualibrate/utils/node/loaders/xarray_loader.py
qualibrate_core-0.6.0.dist-info/METADATA
qualibrate_core-0.6.0.dist-info/WHEEL
qualibrate_core-0.6.0.dist-info/licenses/LICENSE
qualibrate_core-0.6.0.dist-info/RECORD
