Metadata-Version: 2.4
Name: qualibrate-core
Version: 0.6.0
Summary: 
License-File: LICENSE
Author: Quantum Machines
Author-email: info@quantum-machines.co
Requires-Python: >=3.10,<3.13
Classifier: Programming Language :: Python :: 3
Classifier: Programming Language :: Python :: 3.10
Classifier: Programming Language :: Python :: 3.11
Classifier: Programming Language :: Python :: 3.12
Requires-Dist: datamodel-code-generator (>=0.33.0,<0.34.0)
Requires-Dist: jsonpatch (>=1.33,<2.0)
Requires-Dist: jsonpointer (>=3.0.0,<4.0.0)
Requires-Dist: matplotlib (>=3.10.6,<4.0.0)
Requires-Dist: networkx (>=3.4.2,<3.5.0)
Requires-Dist: pydantic (>=2.9.2,<3.0.0)
Requires-Dist: python-json-logger (>=3.2.1,<4.0.0)
Requires-Dist: qualang-tools (>=0.20.0) ; python_version >= "3.10" and python_version < "3.13"
Requires-Dist: qualibrate-config (>=0.1.8,<0.2.0)
Requires-Dist: types-networkx (>=3.4.2.20250527,<3.5.0.0)
